{"frames": {

"slots/anim/1/7":
{
	"frame": {"x":1586,"y":610,"w":118,"h":123},
	"rotated": false,
	"trimmed": true,
	"spriteSourceSize": {"x":0,"y":9,"w":118,"h":123},
	"sourceSize": {"w":118,"h":142}
},
"slots/anim/1/8":
{
	"frame": {"x":1467,"y":733,"w":118,"h":126},
	"rotated": false,
	"trimmed": true,
	"spriteSourceSize": {"x":0,"y":8,"w":118,"h":126},
	"sourceSize": {"w":118,"h":142}
},
"slots/anim/1/9":
{
	"frame": {"x":858,"y":859,"w":118,"h":129},
	"rotated": false,
	"trimmed": true,
	"spriteSourceSize": {"x":0,"y":6,"w":118,"h":129},
	"sourceSize": {"w":118,"h":142}
},
"slots/anim/1/10":
{
	"frame": {"x":627,"y":989,"w":118,"h":132},
	"rotated": false,
	"trimmed": true,
	"spriteSourceSize": {"x":0,"y":5,"w":118,"h":132},
	"sourceSize": {"w":118,"h":142}
},
"slots/anim/1/11":
{
	"frame": {"x":1383,"y":989,"w":118,"h":134},
	"rotated": false,
	"trimmed": true,
	"spriteSourceSize": {"x":0,"y":4,"w":118,"h":134},
	"sourceSize": {"w":118,"h":142}
},
"slots/anim/1/12":
{
	"frame": {"x":629,"y":1395,"w":118,"h":138},
	"rotated": false,
	"trimmed": true,
	"spriteSourceSize": {"x":0,"y":2,"w":118,"h":138},
	"sourceSize": {"w":118,"h":142}
},
"slots/anim/1/13":
{
	"frame": {"x":613,"y":1534,"w":118,"h":140},
	"rotated": false,
	"trimmed": true,
	"spriteSourceSize": {"x":0,"y":1,"w":118,"h":140},
	"sourceSize": {"w":118,"h":142}
},
"slots/anim/1/14":
{
	"frame": {"x":1355,"y":1534,"w":118,"h":142},
	"rotated": false,
	"trimmed": false,
	"spriteSourceSize": {"x":0,"y":0,"w":118,"h":142},
	"sourceSize": {"w":118,"h":142}
},
"slots/anim/1/15":
{
	"frame": {"x":1746,"y":1395,"w":118,"h":139},
	"rotated": false,
	"trimmed": true,
	"spriteSourceSize": {"x":0,"y":1,"w":118,"h":139},
	"sourceSize": {"w":118,"h":142}
},
"slots/anim/1/16":
{
	"frame": {"x":1501,"y":989,"w":118,"h":134},
	"rotated": false,
	"trimmed": true,
	"spriteSourceSize": {"x":0,"y":4,"w":118,"h":134},
	"sourceSize": {"w":118,"h":142}
},
"slots/anim/1/17":
{
	"frame": {"x":1483,"y":859,"w":118,"h":130},
	"rotated": false,
	"trimmed": true,
	"spriteSourceSize": {"x":0,"y":6,"w":118,"h":130},
	"sourceSize": {"w":118,"h":142}
},
"slots/anim/1/18":
{
	"frame": {"x":1349,"y":733,"w":118,"h":126},
	"rotated": false,
	"trimmed": true,
	"spriteSourceSize": {"x":0,"y":8,"w":118,"h":126},
	"sourceSize": {"w":118,"h":142}
},
"slots/anim/2/2":
{
	"frame": {"x":123,"y":0,"w":122,"h":122},
	"rotated": false,
	"trimmed": true,
	"spriteSourceSize": {"x":11,"y":10,"w":122,"h":122},
	"sourceSize": {"w":144,"h":142}
},
"slots/anim/2/3":
{
	"frame": {"x":1465,"y":0,"w":122,"h":122},
	"rotated": false,
	"trimmed": true,
	"spriteSourceSize": {"x":11,"y":10,"w":122,"h":122},
	"sourceSize": {"w":144,"h":142}
},
"slots/anim/2/4":
{
	"frame": {"x":976,"y":122,"w":122,"h":122},
	"rotated": false,
	"trimmed": true,
	"spriteSourceSize": {"x":11,"y":10,"w":122,"h":122},
	"sourceSize": {"w":144,"h":142}
},
"slots/anim/2/5":
{
	"frame": {"x":1220,"y":122,"w":122,"h":122},
	"rotated": false,
	"trimmed": true,
	"spriteSourceSize": {"x":11,"y":10,"w":122,"h":122},
	"sourceSize": {"w":144,"h":142}
},
"slots/anim/2/6":
{
	"frame": {"x":1342,"y":122,"w":122,"h":122},
	"rotated": false,
	"trimmed": true,
	"spriteSourceSize": {"x":11,"y":10,"w":122,"h":122},
	"sourceSize": {"w":144,"h":142}
},
"slots/anim/2/7":
{
	"frame": {"x":1464,"y":122,"w":124,"h":122},
	"rotated": false,
	"trimmed": true,
	"spriteSourceSize": {"x":9,"y":10,"w":124,"h":122},
	"sourceSize": {"w":144,"h":142}
},
"slots/anim/2/8":
{
	"frame": {"x":1588,"y":122,"w":125,"h":122},
	"rotated": false,
	"trimmed": true,
	"spriteSourceSize": {"x":8,"y":10,"w":125,"h":122},
	"sourceSize": {"w":144,"h":142}
},
"slots/anim/2/9":
{
	"frame": {"x":244,"y":733,"w":127,"h":124},
	"rotated": false,
	"trimmed": true,
	"spriteSourceSize": {"x":7,"y":8,"w":127,"h":124},
	"sourceSize": {"w":144,"h":142}
},
"slots/anim/2/10":
{
	"frame": {"x":1585,"y":733,"w":130,"h":126},
	"rotated": false,
	"trimmed": true,
	"spriteSourceSize": {"x":5,"y":7,"w":130,"h":126},
	"sourceSize": {"w":144,"h":142}
},
"slots/anim/2/11":
{
	"frame": {"x":976,"y":859,"w":133,"h":129},
	"rotated": false,
	"trimmed": true,
	"spriteSourceSize": {"x":4,"y":6,"w":133,"h":129},
	"sourceSize": {"w":144,"h":142}
},
"slots/anim/2/12":
{
	"frame": {"x":745,"y":989,"w":136,"h":132},
	"rotated": false,
	"trimmed": true,
	"spriteSourceSize": {"x":2,"y":4,"w":136,"h":132},
	"sourceSize": {"w":144,"h":142}
},
"slots/anim/2/13":
{
	"frame": {"x":394,"y":1123,"w":138,"h":135},
	"rotated": false,
	"trimmed": true,
	"spriteSourceSize": {"x":1,"y":3,"w":138,"h":135},
	"sourceSize": {"w":144,"h":142}
},
"slots/anim/2/14":
{
	"frame": {"x":747,"y":1395,"w":141,"h":138},
	"rotated": false,
	"trimmed": true,
	"spriteSourceSize": {"x":0,"y":1,"w":141,"h":138},
	"sourceSize": {"w":144,"h":142}
},
"slots/anim/2/15":
{
	"frame": {"x":1125,"y":989,"w":138,"h":133},
	"rotated": false,
	"trimmed": true,
	"spriteSourceSize": {"x":1,"y":4,"w":138,"h":133},
	"sourceSize": {"w":144,"h":142}
},
"slots/anim/2/16":
{
	"frame": {"x":1109,"y":859,"w":132,"h":129},
	"rotated": false,
	"trimmed": true,
	"spriteSourceSize": {"x":4,"y":6,"w":132,"h":129},
	"sourceSize": {"w":144,"h":142}
},
"slots/anim/2/17":
{
	"frame": {"x":857,"y":733,"w":128,"h":125},
	"rotated": false,
	"trimmed": true,
	"spriteSourceSize": {"x":6,"y":8,"w":128,"h":125},
	"sourceSize": {"w":144,"h":142}
},
"slots/anim/2/19":
{
	"frame": {"x":0,"y":0,"w":123,"h":122},
	"rotated": false,
	"trimmed": true,
	"spriteSourceSize": {"x":10,"y":10,"w":123,"h":122},
	"sourceSize": {"w":144,"h":142}
},
"slots/anim/2/20":
{
	"frame": {"x":245,"y":0,"w":122,"h":122},
	"rotated": false,
	"trimmed": true,
	"spriteSourceSize": {"x":11,"y":10,"w":122,"h":122},
	"sourceSize": {"w":144,"h":142}
},
"slots/anim/2/21":
{
	"frame": {"x":367,"y":0,"w":122,"h":122},
	"rotated": false,
	"trimmed": true,
	"spriteSourceSize": {"x":11,"y":10,"w":122,"h":122},
	"sourceSize": {"w":144,"h":142}
},
"slots/anim/2/22":
{
	"frame": {"x":489,"y":0,"w":122,"h":122},
	"rotated": false,
	"trimmed": true,
	"spriteSourceSize": {"x":11,"y":10,"w":122,"h":122},
	"sourceSize": {"w":144,"h":142}
},
"slots/anim/2/23":
{
	"frame": {"x":611,"y":0,"w":122,"h":122},
	"rotated": false,
	"trimmed": true,
	"spriteSourceSize": {"x":11,"y":10,"w":122,"h":122},
	"sourceSize": {"w":144,"h":142}
},
"slots/anim/2/24":
{
	"frame": {"x":733,"y":0,"w":122,"h":122},
	"rotated": false,
	"trimmed": true,
	"spriteSourceSize": {"x":11,"y":10,"w":122,"h":122},
	"sourceSize": {"w":144,"h":142}
},
"slots/anim/2/25":
{
	"frame": {"x":855,"y":0,"w":122,"h":122},
	"rotated": false,
	"trimmed": true,
	"spriteSourceSize": {"x":11,"y":10,"w":122,"h":122},
	"sourceSize": {"w":144,"h":142}
},
"slots/anim/2/26":
{
	"frame": {"x":977,"y":0,"w":122,"h":122},
	"rotated": false,
	"trimmed": true,
	"spriteSourceSize": {"x":11,"y":10,"w":122,"h":122},
	"sourceSize": {"w":144,"h":142}
},
"slots/anim/2/27":
{
	"frame": {"x":1099,"y":0,"w":122,"h":122},
	"rotated": false,
	"trimmed": true,
	"spriteSourceSize": {"x":11,"y":10,"w":122,"h":122},
	"sourceSize": {"w":144,"h":142}
},
"slots/anim/2/28":
{
	"frame": {"x":1221,"y":0,"w":122,"h":122},
	"rotated": false,
	"trimmed": true,
	"spriteSourceSize": {"x":11,"y":10,"w":122,"h":122},
	"sourceSize": {"w":144,"h":142}
},
"slots/anim/2/29":
{
	"frame": {"x":1343,"y":0,"w":122,"h":122},
	"rotated": false,
	"trimmed": true,
	"spriteSourceSize": {"x":11,"y":10,"w":122,"h":122},
	"sourceSize": {"w":144,"h":142}
},
"slots/anim/2/30":
{
	"frame": {"x":1587,"y":0,"w":122,"h":122},
	"rotated": false,
	"trimmed": true,
	"spriteSourceSize": {"x":11,"y":10,"w":122,"h":122},
	"sourceSize": {"w":144,"h":142}
},
"slots/anim/2/31":
{
	"frame": {"x":1709,"y":0,"w":122,"h":122},
	"rotated": false,
	"trimmed": true,
	"spriteSourceSize": {"x":11,"y":10,"w":122,"h":122},
	"sourceSize": {"w":144,"h":142}
},
"slots/anim/2/32":
{
	"frame": {"x":0,"y":122,"w":122,"h":122},
	"rotated": false,
	"trimmed": true,
	"spriteSourceSize": {"x":11,"y":10,"w":122,"h":122},
	"sourceSize": {"w":144,"h":142}
},
"slots/anim/2/33":
{
	"frame": {"x":122,"y":122,"w":122,"h":122},
	"rotated": false,
	"trimmed": true,
	"spriteSourceSize": {"x":11,"y":10,"w":122,"h":122},
	"sourceSize": {"w":144,"h":142}
},
"slots/anim/2/34":
{
	"frame": {"x":244,"y":122,"w":122,"h":122},
	"rotated": false,
	"trimmed": true,
	"spriteSourceSize": {"x":11,"y":10,"w":122,"h":122},
	"sourceSize": {"w":144,"h":142}
},
"slots/anim/2/35":
{
	"frame": {"x":366,"y":122,"w":122,"h":122},
	"rotated": false,
	"trimmed": true,
	"spriteSourceSize": {"x":11,"y":10,"w":122,"h":122},
	"sourceSize": {"w":144,"h":142}
},
"slots/anim/2/36":
{
	"frame": {"x":488,"y":122,"w":122,"h":122},
	"rotated": false,
	"trimmed": true,
	"spriteSourceSize": {"x":11,"y":10,"w":122,"h":122},
	"sourceSize": {"w":144,"h":142}
},
"slots/anim/2/37":
{
	"frame": {"x":610,"y":122,"w":122,"h":122},
	"rotated": false,
	"trimmed": true,
	"spriteSourceSize": {"x":11,"y":10,"w":122,"h":122},
	"sourceSize": {"w":144,"h":142}
},
"slots/anim/2/38":
{
	"frame": {"x":732,"y":122,"w":122,"h":122},
	"rotated": false,
	"trimmed": true,
	"spriteSourceSize": {"x":11,"y":10,"w":122,"h":122},
	"sourceSize": {"w":144,"h":142}
},
"slots/anim/2/39":
{
	"frame": {"x":854,"y":122,"w":122,"h":122},
	"rotated": false,
	"trimmed": true,
	"spriteSourceSize": {"x":11,"y":10,"w":122,"h":122},
	"sourceSize": {"w":144,"h":142}
},
"slots/anim/2/40":
{
	"frame": {"x":1098,"y":122,"w":122,"h":122},
	"rotated": false,
	"trimmed": true,
	"spriteSourceSize": {"x":11,"y":10,"w":122,"h":122},
	"sourceSize": {"w":144,"h":142}
},
"slots/anim/3/1":
{
	"frame": {"x":1713,"y":122,"w":120,"h":122},
	"rotated": false,
	"trimmed": true,
	"spriteSourceSize": {"x":0,"y":12,"w":120,"h":122},
	"sourceSize": {"w":120,"h":146}
},
"slots/anim/3/2":
{
	"frame": {"x":0,"y":244,"w":120,"h":122},
	"rotated": false,
	"trimmed": true,
	"spriteSourceSize": {"x":0,"y":12,"w":120,"h":122},
	"sourceSize": {"w":120,"h":146}
},
"slots/anim/3/3":
{
	"frame": {"x":1320,"y":244,"w":120,"h":122},
	"rotated": false,
	"trimmed": true,
	"spriteSourceSize": {"x":0,"y":12,"w":120,"h":122},
	"sourceSize": {"w":120,"h":146}
},
"slots/anim/3/4":
{
	"frame": {"x":720,"y":366,"w":120,"h":122},
	"rotated": false,
	"trimmed": true,
	"spriteSourceSize": {"x":0,"y":12,"w":120,"h":122},
	"sourceSize": {"w":120,"h":146}
},
"slots/anim/3/5":
{
	"frame": {"x":960,"y":366,"w":120,"h":122},
	"rotated": false,
	"trimmed": true,
	"spriteSourceSize": {"x":0,"y":12,"w":120,"h":122},
	"sourceSize": {"w":120,"h":146}
},
"slots/anim/3/6":
{
	"frame": {"x":1704,"y":610,"w":120,"h":123},
	"rotated": false,
	"trimmed": true,
	"spriteSourceSize": {"x":0,"y":11,"w":120,"h":123},
	"sourceSize": {"w":120,"h":146}
},
"slots/anim/3/7":
{
	"frame": {"x":985,"y":733,"w":120,"h":125},
	"rotated": false,
	"trimmed": true,
	"spriteSourceSize": {"x":0,"y":9,"w":120,"h":125},
	"sourceSize": {"w":120,"h":146}
},
"slots/anim/3/8":
{
	"frame": {"x":0,"y":859,"w":120,"h":126},
	"rotated": false,
	"trimmed": true,
	"spriteSourceSize": {"x":0,"y":8,"w":120,"h":126},
	"sourceSize": {"w":120,"h":146}
},
"slots/anim/3/9":
{
	"frame": {"x":738,"y":859,"w":120,"h":128},
	"rotated": false,
	"trimmed": true,
	"spriteSourceSize": {"x":0,"y":7,"w":120,"h":128},
	"sourceSize": {"w":120,"h":146}
},
"slots/anim/3/10":
{
	"frame": {"x":384,"y":989,"w":120,"h":131},
	"rotated": false,
	"trimmed": true,
	"spriteSourceSize": {"x":0,"y":5,"w":120,"h":131},
	"sourceSize": {"w":120,"h":146}
},
"slots/anim/3/11":
{
	"frame": {"x":1619,"y":989,"w":120,"h":134},
	"rotated": false,
	"trimmed": true,
	"spriteSourceSize": {"x":0,"y":4,"w":120,"h":134},
	"sourceSize": {"w":120,"h":146}
},
"slots/anim/3/12":
{
	"frame": {"x":138,"y":1395,"w":120,"h":137},
	"rotated": false,
	"trimmed": true,
	"spriteSourceSize": {"x":0,"y":2,"w":120,"h":137},
	"sourceSize": {"w":120,"h":146}
},
"slots/anim/3/13":
{
	"frame": {"x":0,"y":1534,"w":120,"h":139},
	"rotated": false,
	"trimmed": true,
	"spriteSourceSize": {"x":0,"y":1,"w":120,"h":139},
	"sourceSize": {"w":120,"h":146}
},
"slots/anim/3/14":
{
	"frame": {"x":1473,"y":1534,"w":120,"h":142},
	"rotated": false,
	"trimmed": true,
	"spriteSourceSize": {"x":0,"y":0,"w":120,"h":142},
	"sourceSize": {"w":120,"h":146}
},
"slots/anim/3/15":
{
	"frame": {"x":120,"y":1534,"w":120,"h":139},
	"rotated": false,
	"trimmed": true,
	"spriteSourceSize": {"x":0,"y":1,"w":120,"h":139},
	"sourceSize": {"w":120,"h":146}
},
"slots/anim/3/16":
{
	"frame": {"x":1263,"y":989,"w":120,"h":133},
	"rotated": false,
	"trimmed": true,
	"spriteSourceSize": {"x":0,"y":4,"w":120,"h":133},
	"sourceSize": {"w":120,"h":146}
},
"slots/anim/3/17":
{
	"frame": {"x":1241,"y":859,"w":120,"h":129},
	"rotated": false,
	"trimmed": true,
	"spriteSourceSize": {"x":0,"y":6,"w":120,"h":129},
	"sourceSize": {"w":120,"h":146}
},
"slots/anim/3/18":
{
	"frame": {"x":1715,"y":733,"w":120,"h":126},
	"rotated": false,
	"trimmed": true,
	"spriteSourceSize": {"x":0,"y":8,"w":120,"h":126},
	"sourceSize": {"w":120,"h":146}
},
"slots/anim/3/19":
{
	"frame": {"x":371,"y":733,"w":120,"h":124},
	"rotated": false,
	"trimmed": true,
	"spriteSourceSize": {"x":0,"y":10,"w":120,"h":124},
	"sourceSize": {"w":120,"h":146}
},
"slots/anim/3/20":
{
	"frame": {"x":120,"y":244,"w":120,"h":122},
	"rotated": false,
	"trimmed": true,
	"spriteSourceSize": {"x":0,"y":12,"w":120,"h":122},
	"sourceSize": {"w":120,"h":146}
},
"slots/anim/3/21":
{
	"frame": {"x":240,"y":244,"w":120,"h":122},
	"rotated": false,
	"trimmed": true,
	"spriteSourceSize": {"x":0,"y":12,"w":120,"h":122},
	"sourceSize": {"w":120,"h":146}
},
"slots/anim/3/22":
{
	"frame": {"x":360,"y":244,"w":120,"h":122},
	"rotated": false,
	"trimmed": true,
	"spriteSourceSize": {"x":0,"y":12,"w":120,"h":122},
	"sourceSize": {"w":120,"h":146}
},
"slots/anim/3/23":
{
	"frame": {"x":480,"y":244,"w":120,"h":122},
	"rotated": false,
	"trimmed": true,
	"spriteSourceSize": {"x":0,"y":12,"w":120,"h":122},
	"sourceSize": {"w":120,"h":146}
},
"slots/anim/3/24":
{
	"frame": {"x":600,"y":244,"w":120,"h":122},
	"rotated": false,
	"trimmed": true,
	"spriteSourceSize": {"x":0,"y":12,"w":120,"h":122},
	"sourceSize": {"w":120,"h":146}
},
"slots/anim/3/25":
{
	"frame": {"x":720,"y":244,"w":120,"h":122},
	"rotated": false,
	"trimmed": true,
	"spriteSourceSize": {"x":0,"y":12,"w":120,"h":122},
	"sourceSize": {"w":120,"h":146}
},
"slots/anim/3/26":
{
	"frame": {"x":840,"y":244,"w":120,"h":122},
	"rotated": false,
	"trimmed": true,
	"spriteSourceSize": {"x":0,"y":12,"w":120,"h":122},
	"sourceSize": {"w":120,"h":146}
},
"slots/anim/3/27":
{
	"frame": {"x":960,"y":244,"w":120,"h":122},
	"rotated": false,
	"trimmed": true,
	"spriteSourceSize": {"x":0,"y":12,"w":120,"h":122},
	"sourceSize": {"w":120,"h":146}
},
"slots/anim/3/28":
{
	"frame": {"x":1080,"y":244,"w":120,"h":122},
	"rotated": false,
	"trimmed": true,
	"spriteSourceSize": {"x":0,"y":12,"w":120,"h":122},
	"sourceSize": {"w":120,"h":146}
},
"slots/anim/3/29":
{
	"frame": {"x":1200,"y":244,"w":120,"h":122},
	"rotated": false,
	"trimmed": true,
	"spriteSourceSize": {"x":0,"y":12,"w":120,"h":122},
	"sourceSize": {"w":120,"h":146}
},
"slots/anim/3/30":
{
	"frame": {"x":1440,"y":244,"w":120,"h":122},
	"rotated": false,
	"trimmed": true,
	"spriteSourceSize": {"x":0,"y":12,"w":120,"h":122},
	"sourceSize": {"w":120,"h":146}
},
"slots/anim/3/31":
{
	"frame": {"x":1560,"y":244,"w":120,"h":122},
	"rotated": false,
	"trimmed": true,
	"spriteSourceSize": {"x":0,"y":12,"w":120,"h":122},
	"sourceSize": {"w":120,"h":146}
},
"slots/anim/3/32":
{
	"frame": {"x":1680,"y":244,"w":120,"h":122},
	"rotated": false,
	"trimmed": true,
	"spriteSourceSize": {"x":0,"y":12,"w":120,"h":122},
	"sourceSize": {"w":120,"h":146}
},
"slots/anim/3/33":
{
	"frame": {"x":1800,"y":244,"w":120,"h":122},
	"rotated": false,
	"trimmed": true,
	"spriteSourceSize": {"x":0,"y":12,"w":120,"h":122},
	"sourceSize": {"w":120,"h":146}
},
"slots/anim/3/34":
{
	"frame": {"x":0,"y":366,"w":120,"h":122},
	"rotated": false,
	"trimmed": true,
	"spriteSourceSize": {"x":0,"y":12,"w":120,"h":122},
	"sourceSize": {"w":120,"h":146}
},
"slots/anim/3/35":
{
	"frame": {"x":120,"y":366,"w":120,"h":122},
	"rotated": false,
	"trimmed": true,
	"spriteSourceSize": {"x":0,"y":12,"w":120,"h":122},
	"sourceSize": {"w":120,"h":146}
},
"slots/anim/3/36":
{
	"frame": {"x":240,"y":366,"w":120,"h":122},
	"rotated": false,
	"trimmed": true,
	"spriteSourceSize": {"x":0,"y":12,"w":120,"h":122},
	"sourceSize": {"w":120,"h":146}
},
"slots/anim/3/37":
{
	"frame": {"x":360,"y":366,"w":120,"h":122},
	"rotated": false,
	"trimmed": true,
	"spriteSourceSize": {"x":0,"y":12,"w":120,"h":122},
	"sourceSize": {"w":120,"h":146}
},
"slots/anim/3/38":
{
	"frame": {"x":480,"y":366,"w":120,"h":122},
	"rotated": false,
	"trimmed": true,
	"spriteSourceSize": {"x":0,"y":12,"w":120,"h":122},
	"sourceSize": {"w":120,"h":146}
},
"slots/anim/3/39":
{
	"frame": {"x":600,"y":366,"w":120,"h":122},
	"rotated": false,
	"trimmed": true,
	"spriteSourceSize": {"x":0,"y":12,"w":120,"h":122},
	"sourceSize": {"w":120,"h":146}
},
"slots/anim/3/40":
{
	"frame": {"x":840,"y":366,"w":120,"h":122},
	"rotated": false,
	"trimmed": true,
	"spriteSourceSize": {"x":0,"y":12,"w":120,"h":122},
	"sourceSize": {"w":120,"h":146}
},
"slots/anim/4/1":
{
	"frame": {"x":1080,"y":366,"w":122,"h":122},
	"rotated": false,
	"trimmed": true,
	"spriteSourceSize": {"x":5,"y":10,"w":122,"h":122},
	"sourceSize": {"w":132,"h":142}
},
"slots/anim/4/2":
{
	"frame": {"x":1324,"y":366,"w":122,"h":122},
	"rotated": false,
	"trimmed": true,
	"spriteSourceSize": {"x":5,"y":10,"w":122,"h":122},
	"sourceSize": {"w":132,"h":142}
},
"slots/anim/4/3":
{
	"frame": {"x":732,"y":488,"w":122,"h":122},
	"rotated": false,
	"trimmed": true,
	"spriteSourceSize": {"x":5,"y":10,"w":122,"h":122},
	"sourceSize": {"w":132,"h":142}
},
"slots/anim/4/4":
{
	"frame": {"x":244,"y":610,"w":122,"h":122},
	"rotated": false,
	"trimmed": true,
	"spriteSourceSize": {"x":5,"y":10,"w":122,"h":122},
	"sourceSize": {"w":132,"h":142}
},
"slots/anim/4/5":
{
	"frame": {"x":488,"y":610,"w":122,"h":122},
	"rotated": false,
	"trimmed": true,
	"spriteSourceSize": {"x":5,"y":10,"w":122,"h":122},
	"sourceSize": {"w":132,"h":142}
},
"slots/anim/4/6":
{
	"frame": {"x":610,"y":610,"w":122,"h":122},
	"rotated": false,
	"trimmed": true,
	"spriteSourceSize": {"x":5,"y":10,"w":122,"h":122},
	"sourceSize": {"w":132,"h":142}
},
"slots/anim/4/7":
{
	"frame": {"x":1824,"y":610,"w":122,"h":123},
	"rotated": false,
	"trimmed": true,
	"spriteSourceSize": {"x":5,"y":9,"w":122,"h":123},
	"sourceSize": {"w":132,"h":142}
},
"slots/anim/4/8":
{
	"frame": {"x":120,"y":859,"w":122,"h":126},
	"rotated": false,
	"trimmed": true,
	"spriteSourceSize": {"x":5,"y":8,"w":122,"h":126},
	"sourceSize": {"w":132,"h":142}
},
"slots/anim/4/9":
{
	"frame": {"x":1361,"y":859,"w":122,"h":129},
	"rotated": false,
	"trimmed": true,
	"spriteSourceSize": {"x":5,"y":6,"w":122,"h":129},
	"sourceSize": {"w":132,"h":142}
},
"slots/anim/4/10":
{
	"frame": {"x":504,"y":989,"w":123,"h":131},
	"rotated": false,
	"trimmed": true,
	"spriteSourceSize": {"x":5,"y":5,"w":123,"h":131},
	"sourceSize": {"w":132,"h":142}
},
"slots/anim/4/11":
{
	"frame": {"x":1739,"y":989,"w":124,"h":134},
	"rotated": false,
	"trimmed": true,
	"spriteSourceSize": {"x":5,"y":4,"w":124,"h":134},
	"sourceSize": {"w":132,"h":142}
},
"slots/anim/4/12":
{
	"frame": {"x":258,"y":1395,"w":127,"h":137},
	"rotated": false,
	"trimmed": true,
	"spriteSourceSize": {"x":4,"y":2,"w":127,"h":137},
	"sourceSize": {"w":132,"h":142}
},
"slots/anim/4/13":
{
	"frame": {"x":731,"y":1534,"w":129,"h":140},
	"rotated": false,
	"trimmed": true,
	"spriteSourceSize": {"x":3,"y":1,"w":129,"h":140},
	"sourceSize": {"w":132,"h":142}
},
"slots/anim/4/14":
{
	"frame": {"x":1593,"y":1534,"w":130,"h":142},
	"rotated": false,
	"trimmed": true,
	"spriteSourceSize": {"x":2,"y":0,"w":130,"h":142},
	"sourceSize": {"w":132,"h":142}
},
"slots/anim/4/15":
{
	"frame": {"x":240,"y":1534,"w":127,"h":139},
	"rotated": false,
	"trimmed": true,
	"spriteSourceSize": {"x":4,"y":1,"w":127,"h":139},
	"sourceSize": {"w":132,"h":142}
},
"slots/anim/4/16":
{
	"frame": {"x":0,"y":1123,"w":124,"h":134},
	"rotated": false,
	"trimmed": true,
	"spriteSourceSize": {"x":5,"y":4,"w":124,"h":134},
	"sourceSize": {"w":132,"h":142}
},
"slots/anim/4/17":
{
	"frame": {"x":1601,"y":859,"w":122,"h":130},
	"rotated": false,
	"trimmed": true,
	"spriteSourceSize": {"x":5,"y":6,"w":122,"h":130},
	"sourceSize": {"w":132,"h":142}
},
"slots/anim/4/18":
{
	"frame": {"x":1105,"y":733,"w":122,"h":125},
	"rotated": false,
	"trimmed": true,
	"spriteSourceSize": {"x":5,"y":8,"w":122,"h":125},
	"sourceSize": {"w":132,"h":142}
},
"slots/anim/4/19":
{
	"frame": {"x":1202,"y":366,"w":122,"h":122},
	"rotated": false,
	"trimmed": true,
	"spriteSourceSize": {"x":5,"y":10,"w":122,"h":122},
	"sourceSize": {"w":132,"h":142}
},
"slots/anim/4/20":
{
	"frame": {"x":1446,"y":366,"w":122,"h":122},
	"rotated": false,
	"trimmed": true,
	"spriteSourceSize": {"x":5,"y":10,"w":122,"h":122},
	"sourceSize": {"w":132,"h":142}
},
"slots/anim/4/21":
{
	"frame": {"x":1568,"y":366,"w":122,"h":122},
	"rotated": false,
	"trimmed": true,
	"spriteSourceSize": {"x":5,"y":10,"w":122,"h":122},
	"sourceSize": {"w":132,"h":142}
},
"slots/anim/4/22":
{
	"frame": {"x":1690,"y":366,"w":122,"h":122},
	"rotated": false,
	"trimmed": true,
	"spriteSourceSize": {"x":5,"y":10,"w":122,"h":122},
	"sourceSize": {"w":132,"h":142}
},
"slots/anim/4/23":
{
	"frame": {"x":1812,"y":366,"w":122,"h":122},
	"rotated": false,
	"trimmed": true,
	"spriteSourceSize": {"x":5,"y":10,"w":122,"h":122},
	"sourceSize": {"w":132,"h":142}
},
"slots/anim/4/24":
{
	"frame": {"x":0,"y":488,"w":122,"h":122},
	"rotated": false,
	"trimmed": true,
	"spriteSourceSize": {"x":5,"y":10,"w":122,"h":122},
	"sourceSize": {"w":132,"h":142}
},
"slots/anim/4/25":
{
	"frame": {"x":122,"y":488,"w":122,"h":122},
	"rotated": false,
	"trimmed": true,
	"spriteSourceSize": {"x":5,"y":10,"w":122,"h":122},
	"sourceSize": {"w":132,"h":142}
},
"slots/anim/4/26":
{
	"frame": {"x":244,"y":488,"w":122,"h":122},
	"rotated": false,
	"trimmed": true,
	"spriteSourceSize": {"x":5,"y":10,"w":122,"h":122},
	"sourceSize": {"w":132,"h":142}
},
"slots/anim/4/27":
{
	"frame": {"x":366,"y":488,"w":122,"h":122},
	"rotated": false,
	"trimmed": true,
	"spriteSourceSize": {"x":5,"y":10,"w":122,"h":122},
	"sourceSize": {"w":132,"h":142}
},
"slots/anim/4/28":
{
	"frame": {"x":488,"y":488,"w":122,"h":122},
	"rotated": false,
	"trimmed": true,
	"spriteSourceSize": {"x":5,"y":10,"w":122,"h":122},
	"sourceSize": {"w":132,"h":142}
},
"slots/anim/4/29":
{
	"frame": {"x":610,"y":488,"w":122,"h":122},
	"rotated": false,
	"trimmed": true,
	"spriteSourceSize": {"x":5,"y":10,"w":122,"h":122},
	"sourceSize": {"w":132,"h":142}
},
"slots/anim/4/30":
{
	"frame": {"x":854,"y":488,"w":122,"h":122},
	"rotated": false,
	"trimmed": true,
	"spriteSourceSize": {"x":5,"y":10,"w":122,"h":122},
	"sourceSize": {"w":132,"h":142}
},
"slots/anim/4/31":
{
	"frame": {"x":976,"y":488,"w":122,"h":122},
	"rotated": false,
	"trimmed": true,
	"spriteSourceSize": {"x":5,"y":10,"w":122,"h":122},
	"sourceSize": {"w":132,"h":142}
},
"slots/anim/4/32":
{
	"frame": {"x":1098,"y":488,"w":122,"h":122},
	"rotated": false,
	"trimmed": true,
	"spriteSourceSize": {"x":5,"y":10,"w":122,"h":122},
	"sourceSize": {"w":132,"h":142}
},
"slots/anim/4/33":
{
	"frame": {"x":1220,"y":488,"w":122,"h":122},
	"rotated": false,
	"trimmed": true,
	"spriteSourceSize": {"x":5,"y":10,"w":122,"h":122},
	"sourceSize": {"w":132,"h":142}
},
"slots/anim/4/34":
{
	"frame": {"x":1342,"y":488,"w":122,"h":122},
	"rotated": false,
	"trimmed": true,
	"spriteSourceSize": {"x":5,"y":10,"w":122,"h":122},
	"sourceSize": {"w":132,"h":142}
},
"slots/anim/4/35":
{
	"frame": {"x":1464,"y":488,"w":122,"h":122},
	"rotated": false,
	"trimmed": true,
	"spriteSourceSize": {"x":5,"y":10,"w":122,"h":122},
	"sourceSize": {"w":132,"h":142}
},
"slots/anim/4/36":
{
	"frame": {"x":1586,"y":488,"w":122,"h":122},
	"rotated": false,
	"trimmed": true,
	"spriteSourceSize": {"x":5,"y":10,"w":122,"h":122},
	"sourceSize": {"w":132,"h":142}
},
"slots/anim/4/37":
{
	"frame": {"x":1708,"y":488,"w":122,"h":122},
	"rotated": false,
	"trimmed": true,
	"spriteSourceSize": {"x":5,"y":10,"w":122,"h":122},
	"sourceSize": {"w":132,"h":142}
},
"slots/anim/4/38":
{
	"frame": {"x":0,"y":610,"w":122,"h":122},
	"rotated": false,
	"trimmed": true,
	"spriteSourceSize": {"x":5,"y":10,"w":122,"h":122},
	"sourceSize": {"w":132,"h":142}
},
"slots/anim/4/39":
{
	"frame": {"x":122,"y":610,"w":122,"h":122},
	"rotated": false,
	"trimmed": true,
	"spriteSourceSize": {"x":5,"y":10,"w":122,"h":122},
	"sourceSize": {"w":132,"h":142}
},
"slots/anim/4/40":
{
	"frame": {"x":366,"y":610,"w":122,"h":122},
	"rotated": false,
	"trimmed": true,
	"spriteSourceSize": {"x":5,"y":10,"w":122,"h":122},
	"sourceSize": {"w":132,"h":142}
},
"slots/anim/9/1":
{
	"frame": {"x":732,"y":610,"w":122,"h":122},
	"rotated": false,
	"trimmed": true,
	"spriteSourceSize": {"x":3,"y":11,"w":122,"h":122},
	"sourceSize": {"w":128,"h":144}
},
"slots/anim/9/2":
{
	"frame": {"x":854,"y":610,"w":122,"h":122},
	"rotated": false,
	"trimmed": true,
	"spriteSourceSize": {"x":3,"y":11,"w":122,"h":122},
	"sourceSize": {"w":128,"h":144}
},
"slots/anim/9/3":
{
	"frame": {"x":976,"y":610,"w":122,"h":122},
	"rotated": false,
	"trimmed": true,
	"spriteSourceSize": {"x":3,"y":11,"w":122,"h":122},
	"sourceSize": {"w":128,"h":144}
},
"slots/anim/9/4":
{
	"frame": {"x":122,"y":733,"w":122,"h":123},
	"rotated": false,
	"trimmed": true,
	"spriteSourceSize": {"x":3,"y":10,"w":122,"h":123},
	"sourceSize": {"w":128,"h":144}
},
"slots/anim/9/5":
{
	"frame": {"x":491,"y":733,"w":122,"h":124},
	"rotated": false,
	"trimmed": true,
	"spriteSourceSize": {"x":3,"y":9,"w":122,"h":124},
	"sourceSize": {"w":128,"h":144}
},
"slots/anim/9/6":
{
	"frame": {"x":364,"y":859,"w":122,"h":127},
	"rotated": false,
	"trimmed": true,
	"spriteSourceSize": {"x":3,"y":8,"w":122,"h":127},
	"sourceSize": {"w":128,"h":144}
},
"slots/anim/9/7":
{
	"frame": {"x":0,"y":989,"w":122,"h":130},
	"rotated": false,
	"trimmed": true,
	"spriteSourceSize": {"x":3,"y":6,"w":122,"h":130},
	"sourceSize": {"w":128,"h":144}
},
"slots/anim/9/8":
{
	"frame": {"x":1003,"y":989,"w":122,"h":132},
	"rotated": false,
	"trimmed": true,
	"spriteSourceSize": {"x":3,"y":5,"w":122,"h":132},
	"sourceSize": {"w":128,"h":144}
},
"slots/anim/9/9":
{
	"frame": {"x":654,"y":1123,"w":123,"h":135},
	"rotated": false,
	"trimmed": true,
	"spriteSourceSize": {"x":2,"y":3,"w":123,"h":135},
	"sourceSize": {"w":128,"h":144}
},
"slots/anim/9/10":
{
	"frame": {"x":888,"y":1395,"w":124,"h":138},
	"rotated": false,
	"trimmed": true,
	"spriteSourceSize": {"x":1,"y":2,"w":124,"h":138},
	"sourceSize": {"w":128,"h":144}
},
"slots/anim/9/11":
{
	"frame": {"x":1107,"y":1534,"w":126,"h":141},
	"rotated": false,
	"trimmed": true,
	"spriteSourceSize": {"x":0,"y":0,"w":126,"h":141},
	"sourceSize": {"w":128,"h":144}
},
"slots/anim/9/12":
{
	"frame": {"x":860,"y":1534,"w":125,"h":140},
	"rotated": false,
	"trimmed": true,
	"spriteSourceSize": {"x":0,"y":1,"w":125,"h":140},
	"sourceSize": {"w":128,"h":144}
},
"slots/anim/9/13":
{
	"frame": {"x":367,"y":1534,"w":124,"h":139},
	"rotated": false,
	"trimmed": true,
	"spriteSourceSize": {"x":1,"y":1,"w":124,"h":139},
	"sourceSize": {"w":128,"h":144}
},
"slots/anim/9/14":
{
	"frame": {"x":1012,"y":1395,"w":123,"h":138},
	"rotated": false,
	"trimmed": true,
	"spriteSourceSize": {"x":2,"y":2,"w":123,"h":138},
	"sourceSize": {"w":128,"h":144}
},
"slots/anim/9/15":
{
	"frame": {"x":1135,"y":1395,"w":123,"h":138},
	"rotated": false,
	"trimmed": true,
	"spriteSourceSize": {"x":2,"y":2,"w":123,"h":138},
	"sourceSize": {"w":128,"h":144}
},
"slots/anim/9/16":
{
	"frame": {"x":1258,"y":1395,"w":122,"h":138},
	"rotated": false,
	"trimmed": true,
	"spriteSourceSize": {"x":3,"y":2,"w":122,"h":138},
	"sourceSize": {"w":128,"h":144}
},
"slots/anim/9/17":
{
	"frame": {"x":1380,"y":1395,"w":122,"h":138},
	"rotated": false,
	"trimmed": true,
	"spriteSourceSize": {"x":3,"y":2,"w":122,"h":138},
	"sourceSize": {"w":128,"h":144}
},
"slots/anim/9/18":
{
	"frame": {"x":385,"y":1395,"w":122,"h":137},
	"rotated": false,
	"trimmed": true,
	"spriteSourceSize": {"x":3,"y":3,"w":122,"h":137},
	"sourceSize": {"w":128,"h":144}
},
"slots/anim/9/19":
{
	"frame": {"x":1502,"y":1395,"w":122,"h":138},
	"rotated": false,
	"trimmed": true,
	"spriteSourceSize": {"x":3,"y":3,"w":122,"h":138},
	"sourceSize": {"w":128,"h":144}
},
"slots/anim/9/20":
{
	"frame": {"x":1624,"y":1395,"w":122,"h":138},
	"rotated": false,
	"trimmed": true,
	"spriteSourceSize": {"x":3,"y":3,"w":122,"h":138},
	"sourceSize": {"w":128,"h":144}
},
"slots/anim/9/21":
{
	"frame": {"x":985,"y":1534,"w":122,"h":140},
	"rotated": false,
	"trimmed": true,
	"spriteSourceSize": {"x":3,"y":2,"w":122,"h":140},
	"sourceSize": {"w":128,"h":144}
},
"slots/anim/9/22":
{
	"frame": {"x":1233,"y":1534,"w":122,"h":141},
	"rotated": false,
	"trimmed": true,
	"spriteSourceSize": {"x":3,"y":1,"w":122,"h":141},
	"sourceSize": {"w":128,"h":144}
},
"slots/anim/9/23":
{
	"frame": {"x":1723,"y":1534,"w":122,"h":143},
	"rotated": false,
	"trimmed": true,
	"spriteSourceSize": {"x":3,"y":0,"w":122,"h":143},
	"sourceSize": {"w":128,"h":144}
},
"slots/anim/9/24":
{
	"frame": {"x":491,"y":1534,"w":122,"h":139},
	"rotated": false,
	"trimmed": true,
	"spriteSourceSize": {"x":3,"y":2,"w":122,"h":139},
	"sourceSize": {"w":128,"h":144}
},
"slots/anim/9/25":
{
	"frame": {"x":507,"y":1395,"w":122,"h":137},
	"rotated": false,
	"trimmed": true,
	"spriteSourceSize": {"x":3,"y":3,"w":122,"h":137},
	"sourceSize": {"w":128,"h":144}
},
"slots/anim/9/26":
{
	"frame": {"x":532,"y":1123,"w":122,"h":135},
	"rotated": false,
	"trimmed": true,
	"spriteSourceSize": {"x":3,"y":4,"w":122,"h":135},
	"sourceSize": {"w":128,"h":144}
},
"slots/anim/9/27":
{
	"frame": {"x":881,"y":989,"w":122,"h":132},
	"rotated": false,
	"trimmed": true,
	"spriteSourceSize": {"x":3,"y":6,"w":122,"h":132},
	"sourceSize": {"w":128,"h":144}
},
"slots/anim/9/28":
{
	"frame": {"x":1723,"y":859,"w":122,"h":130},
	"rotated": false,
	"trimmed": true,
	"spriteSourceSize": {"x":3,"y":7,"w":122,"h":130},
	"sourceSize": {"w":128,"h":144}
},
"slots/anim/9/29":
{
	"frame": {"x":242,"y":859,"w":122,"h":127},
	"rotated": false,
	"trimmed": true,
	"spriteSourceSize": {"x":3,"y":8,"w":122,"h":127},
	"sourceSize": {"w":128,"h":144}
},
"slots/anim/9/30":
{
	"frame": {"x":1227,"y":733,"w":122,"h":125},
	"rotated": false,
	"trimmed": true,
	"spriteSourceSize": {"x":3,"y":9,"w":122,"h":125},
	"sourceSize": {"w":128,"h":144}
},
"slots/anim/9/31":
{
	"frame": {"x":0,"y":733,"w":122,"h":123},
	"rotated": false,
	"trimmed": true,
	"spriteSourceSize": {"x":3,"y":10,"w":122,"h":123},
	"sourceSize": {"w":128,"h":144}
},
"slots/anim/9/32":
{
	"frame": {"x":1098,"y":610,"w":122,"h":122},
	"rotated": false,
	"trimmed": true,
	"spriteSourceSize": {"x":3,"y":11,"w":122,"h":122},
	"sourceSize": {"w":128,"h":144}
},
"slots/anim/9/33":
{
	"frame": {"x":1220,"y":610,"w":122,"h":122},
	"rotated": false,
	"trimmed": true,
	"spriteSourceSize": {"x":3,"y":11,"w":122,"h":122},
	"sourceSize": {"w":128,"h":144}
},
"slots/anim/9/34":
{
	"frame": {"x":1342,"y":610,"w":122,"h":122},
	"rotated": false,
	"trimmed": true,
	"spriteSourceSize": {"x":3,"y":11,"w":122,"h":122},
	"sourceSize": {"w":128,"h":144}
},
"slots/anim/9/35":
{
	"frame": {"x":1464,"y":610,"w":122,"h":122},
	"rotated": false,
	"trimmed": true,
	"spriteSourceSize": {"x":3,"y":11,"w":122,"h":122},
	"sourceSize": {"w":128,"h":144}
},
"slots/anim/12/4":
{
	"frame": {"x":735,"y":733,"w":122,"h":125},
	"rotated": false,
	"trimmed": true,
	"spriteSourceSize": {"x":8,"y":5,"w":122,"h":125},
	"sourceSize": {"w":138,"h":136}
},
"slots/anim/12/5":
{
	"frame": {"x":612,"y":859,"w":126,"h":128},
	"rotated": false,
	"trimmed": true,
	"spriteSourceSize": {"x":6,"y":4,"w":126,"h":128},
	"sourceSize": {"w":138,"h":136}
},
"slots/anim/12/6":
{
	"frame": {"x":253,"y":989,"w":131,"h":131},
	"rotated": false,
	"trimmed": true,
	"spriteSourceSize": {"x":4,"y":2,"w":131,"h":131},
	"sourceSize": {"w":138,"h":136}
},
"slots/anim/12/7":
{
	"frame": {"x":259,"y":1123,"w":135,"h":135},
	"rotated": false,
	"trimmed": true,
	"spriteSourceSize": {"x":2,"y":0,"w":135,"h":135},
	"sourceSize": {"w":138,"h":136}
},
"slots/anim/12/8":
{
	"frame": {"x":1794,"y":1259,"w":138,"h":136},
	"rotated": false,
	"trimmed": false,
	"spriteSourceSize": {"x":0,"y":0,"w":138,"h":136},
	"sourceSize": {"w":138,"h":136}
},
"slots/anim/12/9":
{
	"frame": {"x":0,"y":1395,"w":138,"h":136},
	"rotated": false,
	"trimmed": false,
	"spriteSourceSize": {"x":0,"y":0,"w":138,"h":136},
	"sourceSize": {"w":138,"h":136}
},
"slots/anim/12/10":
{
	"frame": {"x":777,"y":1123,"w":138,"h":136},
	"rotated": false,
	"trimmed": false,
	"spriteSourceSize": {"x":0,"y":0,"w":138,"h":136},
	"sourceSize": {"w":138,"h":136}
},
"slots/anim/12/11":
{
	"frame": {"x":915,"y":1123,"w":138,"h":136},
	"rotated": false,
	"trimmed": false,
	"spriteSourceSize": {"x":0,"y":0,"w":138,"h":136},
	"sourceSize": {"w":138,"h":136}
},
"slots/anim/12/12":
{
	"frame": {"x":1053,"y":1123,"w":138,"h":136},
	"rotated": false,
	"trimmed": false,
	"spriteSourceSize": {"x":0,"y":0,"w":138,"h":136},
	"sourceSize": {"w":138,"h":136}
},
"slots/anim/12/13":
{
	"frame": {"x":1191,"y":1123,"w":138,"h":136},
	"rotated": false,
	"trimmed": false,
	"spriteSourceSize": {"x":0,"y":0,"w":138,"h":136},
	"sourceSize": {"w":138,"h":136}
},
"slots/anim/12/14":
{
	"frame": {"x":1329,"y":1123,"w":138,"h":136},
	"rotated": false,
	"trimmed": false,
	"spriteSourceSize": {"x":0,"y":0,"w":138,"h":136},
	"sourceSize": {"w":138,"h":136}
},
"slots/anim/12/15":
{
	"frame": {"x":1467,"y":1123,"w":138,"h":136},
	"rotated": false,
	"trimmed": false,
	"spriteSourceSize": {"x":0,"y":0,"w":138,"h":136},
	"sourceSize": {"w":138,"h":136}
},
"slots/anim/12/16":
{
	"frame": {"x":1605,"y":1123,"w":138,"h":136},
	"rotated": false,
	"trimmed": false,
	"spriteSourceSize": {"x":0,"y":0,"w":138,"h":136},
	"sourceSize": {"w":138,"h":136}
},
"slots/anim/12/17":
{
	"frame": {"x":1743,"y":1123,"w":138,"h":136},
	"rotated": false,
	"trimmed": false,
	"spriteSourceSize": {"x":0,"y":0,"w":138,"h":136},
	"sourceSize": {"w":138,"h":136}
},
"slots/anim/12/18":
{
	"frame": {"x":0,"y":1259,"w":138,"h":136},
	"rotated": false,
	"trimmed": false,
	"spriteSourceSize": {"x":0,"y":0,"w":138,"h":136},
	"sourceSize": {"w":138,"h":136}
},
"slots/anim/12/19":
{
	"frame": {"x":138,"y":1259,"w":138,"h":136},
	"rotated": false,
	"trimmed": false,
	"spriteSourceSize": {"x":0,"y":0,"w":138,"h":136},
	"sourceSize": {"w":138,"h":136}
},
"slots/anim/12/20":
{
	"frame": {"x":276,"y":1259,"w":138,"h":136},
	"rotated": false,
	"trimmed": false,
	"spriteSourceSize": {"x":0,"y":0,"w":138,"h":136},
	"sourceSize": {"w":138,"h":136}
},
"slots/anim/12/21":
{
	"frame": {"x":414,"y":1259,"w":138,"h":136},
	"rotated": false,
	"trimmed": false,
	"spriteSourceSize": {"x":0,"y":0,"w":138,"h":136},
	"sourceSize": {"w":138,"h":136}
},
"slots/anim/12/22":
{
	"frame": {"x":552,"y":1259,"w":138,"h":136},
	"rotated": false,
	"trimmed": false,
	"spriteSourceSize": {"x":0,"y":0,"w":138,"h":136},
	"sourceSize": {"w":138,"h":136}
},
"slots/anim/12/23":
{
	"frame": {"x":690,"y":1259,"w":138,"h":136},
	"rotated": false,
	"trimmed": false,
	"spriteSourceSize": {"x":0,"y":0,"w":138,"h":136},
	"sourceSize": {"w":138,"h":136}
},
"slots/anim/12/24":
{
	"frame": {"x":828,"y":1259,"w":138,"h":136},
	"rotated": false,
	"trimmed": false,
	"spriteSourceSize": {"x":0,"y":0,"w":138,"h":136},
	"sourceSize": {"w":138,"h":136}
},
"slots/anim/12/25":
{
	"frame": {"x":966,"y":1259,"w":138,"h":136},
	"rotated": false,
	"trimmed": false,
	"spriteSourceSize": {"x":0,"y":0,"w":138,"h":136},
	"sourceSize": {"w":138,"h":136}
},
"slots/anim/12/26":
{
	"frame": {"x":1104,"y":1259,"w":138,"h":136},
	"rotated": false,
	"trimmed": false,
	"spriteSourceSize": {"x":0,"y":0,"w":138,"h":136},
	"sourceSize": {"w":138,"h":136}
},
"slots/anim/12/27":
{
	"frame": {"x":1242,"y":1259,"w":138,"h":136},
	"rotated": false,
	"trimmed": false,
	"spriteSourceSize": {"x":0,"y":0,"w":138,"h":136},
	"sourceSize": {"w":138,"h":136}
},
"slots/anim/12/28":
{
	"frame": {"x":1380,"y":1259,"w":138,"h":136},
	"rotated": false,
	"trimmed": false,
	"spriteSourceSize": {"x":0,"y":0,"w":138,"h":136},
	"sourceSize": {"w":138,"h":136}
},
"slots/anim/12/29":
{
	"frame": {"x":1518,"y":1259,"w":138,"h":136},
	"rotated": false,
	"trimmed": false,
	"spriteSourceSize": {"x":0,"y":0,"w":138,"h":136},
	"sourceSize": {"w":138,"h":136}
},
"slots/anim/12/30":
{
	"frame": {"x":1656,"y":1259,"w":138,"h":136},
	"rotated": false,
	"trimmed": false,
	"spriteSourceSize": {"x":0,"y":0,"w":138,"h":136},
	"sourceSize": {"w":138,"h":136}
},
"slots/anim/12/31":
{
	"frame": {"x":124,"y":1123,"w":135,"h":135},
	"rotated": false,
	"trimmed": true,
	"spriteSourceSize": {"x":2,"y":0,"w":135,"h":135},
	"sourceSize": {"w":138,"h":136}
},
"slots/anim/12/32":
{
	"frame": {"x":122,"y":989,"w":131,"h":131},
	"rotated": false,
	"trimmed": true,
	"spriteSourceSize": {"x":4,"y":2,"w":131,"h":131},
	"sourceSize": {"w":138,"h":136}
},
"slots/anim/12/33":
{
	"frame": {"x":486,"y":859,"w":126,"h":128},
	"rotated": false,
	"trimmed": true,
	"spriteSourceSize": {"x":6,"y":4,"w":126,"h":128},
	"sourceSize": {"w":138,"h":136}
},
"slots/anim/12/34":
{
	"frame": {"x":613,"y":733,"w":122,"h":125},
	"rotated": false,
	"trimmed": true,
	"spriteSourceSize": {"x":8,"y":5,"w":122,"h":125},
	"sourceSize": {"w":138,"h":136}
}},
"animations": {
	"slots/anim/1": ["slots/anim/1/7","slots/anim/1/8","slots/anim/1/9","slots/anim/1/10","slots/anim/1/11","slots/anim/1/12","slots/anim/1/13","slots/anim/1/14","slots/anim/1/15","slots/anim/1/16","slots/anim/1/17","slots/anim/1/18"],
	"slots/anim/12": ["slots/anim/12/4","slots/anim/12/5","slots/anim/12/6","slots/anim/12/7","slots/anim/12/8","slots/anim/12/9","slots/anim/12/10","slots/anim/12/11","slots/anim/12/12","slots/anim/12/13","slots/anim/12/14","slots/anim/12/15","slots/anim/12/16","slots/anim/12/17","slots/anim/12/18","slots/anim/12/19","slots/anim/12/20","slots/anim/12/21","slots/anim/12/22","slots/anim/12/23","slots/anim/12/24","slots/anim/12/25","slots/anim/12/26","slots/anim/12/27","slots/anim/12/28","slots/anim/12/29","slots/anim/12/30","slots/anim/12/31","slots/anim/12/32","slots/anim/12/33","slots/anim/12/34"],
	"slots/anim/2": ["slots/anim/2/2","slots/anim/2/3","slots/anim/2/4","slots/anim/2/5","slots/anim/2/6","slots/anim/2/7","slots/anim/2/8","slots/anim/2/9","slots/anim/2/10","slots/anim/2/11","slots/anim/2/12","slots/anim/2/13","slots/anim/2/14","slots/anim/2/15","slots/anim/2/16","slots/anim/2/17","slots/anim/2/19","slots/anim/2/20","slots/anim/2/21","slots/anim/2/22","slots/anim/2/23","slots/anim/2/24","slots/anim/2/25","slots/anim/2/26","slots/anim/2/27","slots/anim/2/28","slots/anim/2/29","slots/anim/2/30","slots/anim/2/31","slots/anim/2/32","slots/anim/2/33","slots/anim/2/34","slots/anim/2/35","slots/anim/2/36","slots/anim/2/37","slots/anim/2/38","slots/anim/2/39","slots/anim/2/40"],
	"slots/anim/3": ["slots/anim/3/1","slots/anim/3/2","slots/anim/3/3","slots/anim/3/4","slots/anim/3/5","slots/anim/3/6","slots/anim/3/7","slots/anim/3/8","slots/anim/3/9","slots/anim/3/10","slots/anim/3/11","slots/anim/3/12","slots/anim/3/13","slots/anim/3/14","slots/anim/3/15","slots/anim/3/16","slots/anim/3/17","slots/anim/3/18","slots/anim/3/19","slots/anim/3/20","slots/anim/3/21","slots/anim/3/22","slots/anim/3/23","slots/anim/3/24","slots/anim/3/25","slots/anim/3/26","slots/anim/3/27","slots/anim/3/28","slots/anim/3/29","slots/anim/3/30","slots/anim/3/31","slots/anim/3/32","slots/anim/3/33","slots/anim/3/34","slots/anim/3/35","slots/anim/3/36","slots/anim/3/37","slots/anim/3/38","slots/anim/3/39","slots/anim/3/40"],
	"slots/anim/4": ["slots/anim/4/1","slots/anim/4/2","slots/anim/4/3","slots/anim/4/4","slots/anim/4/5","slots/anim/4/6","slots/anim/4/7","slots/anim/4/8","slots/anim/4/9","slots/anim/4/10","slots/anim/4/11","slots/anim/4/12","slots/anim/4/13","slots/anim/4/14","slots/anim/4/15","slots/anim/4/16","slots/anim/4/17","slots/anim/4/18","slots/anim/4/19","slots/anim/4/20","slots/anim/4/21","slots/anim/4/22","slots/anim/4/23","slots/anim/4/24","slots/anim/4/25","slots/anim/4/26","slots/anim/4/27","slots/anim/4/28","slots/anim/4/29","slots/anim/4/30","slots/anim/4/31","slots/anim/4/32","slots/anim/4/33","slots/anim/4/34","slots/anim/4/35","slots/anim/4/36","slots/anim/4/37","slots/anim/4/38","slots/anim/4/39","slots/anim/4/40"],
	"slots/anim/9": ["slots/anim/9/1","slots/anim/9/2","slots/anim/9/3","slots/anim/9/4","slots/anim/9/5","slots/anim/9/6","slots/anim/9/7","slots/anim/9/8","slots/anim/9/9","slots/anim/9/10","slots/anim/9/11","slots/anim/9/12","slots/anim/9/13","slots/anim/9/14","slots/anim/9/15","slots/anim/9/16","slots/anim/9/17","slots/anim/9/18","slots/anim/9/19","slots/anim/9/20","slots/anim/9/21","slots/anim/9/22","slots/anim/9/23","slots/anim/9/24","slots/anim/9/25","slots/anim/9/26","slots/anim/9/27","slots/anim/9/28","slots/anim/9/29","slots/anim/9/30","slots/anim/9/31","slots/anim/9/32","slots/anim/9/33","slots/anim/9/34","slots/anim/9/35"]
},
"meta": {
	"app": "https://www.codeandweb.com/texturepacker",
	"version": "1.0",
	"image": "slots-1.png",
	"format": "RGBA8888",
	"size": {"w":1946,"h":1677},
	"scale": "0.2",
	"related_multi_packs": [ "slots-0.json" ],
	"smartupdate": "$TexturePacker:SmartUpdate:0a99a6f69d9282afa4d72fa29d19e75f:64d7e68fd447a65db8845583811ef658:02fa1d5c14dc3b582487cc3cfb05c4ba$"
}
}
